ncas.py
ncas-1.2.0.dist-info/licenses/LICENSE
ncas-1.2.0.dist-info/METADATA
ncas-1.2.0.dist-info/WHEEL
ncas-1.2.0.dist-info/entry_points.txt
ncas-1.2.0.dist-info/top_level.txt
ncas-1.2.0.dist-info/RECORD
