Metadata-Version: 2.4
Name: ncas
Version: 1.2.0
Summary: A Netsh Command Automation Script for Wi-Fi management
Home-page: https://github.com/sub-limal/ncas
Author: sub-limal
Classifier: Programming Language :: Python :: 3
Classifier: License :: OSI Approved :: MIT License
Classifier: Operating System :: Microsoft :: Windows
License-File: LICENSE
Requires-Dist: terminaltables
Requires-Dist: colorama
Requires-Dist: qrcode
Dynamic: author
Dynamic: classifier
Dynamic: description
Dynamic: description-content-type
Dynamic: home-page
Dynamic: license-file
Dynamic: requires-dist
Dynamic: summary
